serverlesshelper/__init__.py
serverlesshelper/creds.py
serverlesshelper/deploy.py
serverlesshelper/logs.py
serverlesshelper-1.3.0.dist-info/METADATA
serverlesshelper-1.3.0.dist-info/WHEEL
serverlesshelper-1.3.0.dist-info/entry_points.txt
serverlesshelper-1.3.0.dist-info/top_level.txt
serverlesshelper-1.3.0.dist-info/RECORD
