Metadata-Version: 2.1
Name: serverlesshelper
Version: 1.3.0
Summary: UNKNOWN
Home-page: UNKNOWN
Author: Rajiv Sah
Author-email: rajiv.shah01234@gmail.com
License: MIT
Platform: UNKNOWN
Requires-Dist: autopep8 (==1.6.0)
Requires-Dist: prompt-toolkit (==3.0.30)
Requires-Dist: pycodestyle (==2.9.1)
Requires-Dist: ruamel.yaml (==0.17.21)
Requires-Dist: ruamel.yaml.clib (==0.2.6)
Requires-Dist: termcolor (==1.1.0)
Requires-Dist: toml (==0.10.2)
Requires-Dist: wcwidth (==0.2.5)
